setup.cfg
setup.py
langassist_model_engine/__init__.py
langassist_model_engine/constants.py
langassist_model_engine/train.py
langassist_model_engine.egg-info/PKG-INFO
langassist_model_engine.egg-info/SOURCES.txt
langassist_model_engine.egg-info/dependency_links.txt
langassist_model_engine.egg-info/requires.txt
langassist_model_engine.egg-info/top_level.txt
langassist_model_engine/native_lang_identification/__init__.py
langassist_model_engine/native_lang_identification/data/__init__.py
langassist_model_engine/native_lang_identification/data/prep_data.py
langassist_model_engine/native_lang_identification/model/__init__.py
langassist_model_engine/native_lang_identification/model/base.py
langassist_model_engine/native_lang_identification/model/logireg.py
langassist_model_engine/native_lang_identification/model/ss_model.py
langassist_model_engine/nlp_utils/__init__.py
langassist_model_engine/nlp_utils/ngram.py
langassist_model_engine/nlp_utils/tokenize.py
langassist_model_engine/nlp_utils/features/__init__.py
langassist_model_engine/nlp_utils/features/sentence_features.py
langassist_model_engine/nlp_utils/features/builders/__init__.py
langassist_model_engine/nlp_utils/features/builders/base.py
langassist_model_engine/nlp_utils/features/builders/get_builder.py
langassist_model_engine/nlp_utils/features/builders/hash_featurizer.py
langassist_model_engine/nlp_utils/features/builders/vocab_featurizer.py