Metadata-Version: 1.2
Name: langassist-model-engine
Version: 0.1.1
Summary: For building and maintaining the ML models in LangAssist
Home-page: https://langassist.rorybyrne.me
Author: Rory Byrne
Author-email: rory.byrne57@mail.dcu.ie
License: UNKNOWN
Platform: UNKNOWN
Requires-Python: >=3.6
